[
  {
    "id": "hunyuan_zaimai",
    "name": "混元载脉图",
    "desc": "混元为图、脉络为载，以天地之力重塑己身经脉山河。",
    "grade": "earth",
    "category": "internal",
    "realmLv": 27,
    "layers": [
      {
        "level": 1,
        "expFactor": 224,
        "attrs": {
          "spirit": 20,
          "talent": 20,
          "meridians": 22
        }
      },
      {
        "level": 2,
        "expFactor": 248,
        "attrs": {
          "spirit": 20,
          "talent": 20,
          "meridians": 22
        }
      },
      {
        "level": 3,
        "expFactor": 276,
        "attrs": {
          "spirit": 20,
          "talent": 20,
          "meridians": 23
        }
      },
      {
        "level": 4,
        "expFactor": 308,
        "attrs": {
          "spirit": 20,
          "talent": 20,
          "meridians": 23
        }
      },
      {
        "level": 5,
        "expFactor": 344,
        "attrs": {
          "spirit": 20,
          "talent": 20,
          "meridians": 23
        }
      },
      {
        "level": 6,
        "expFactor": 384,
        "attrs": {
          "spirit": 20,
          "talent": 20,
          "meridians": 23
        }
      },
      {
        "level": 7,
        "expFactor": 428,
        "attrs": {
          "spirit": 20,
          "talent": 20,
          "meridians": 23
        }
      },
      {
        "level": 8,
        "expFactor": 476,
        "attrs": {
          "spirit": 20,
          "talent": 20,
          "meridians": 23
        }
      },
      {
        "level": 9,
        "expFactor": 532,
        "attrs": {
          "spirit": 20,
          "talent": 20,
          "meridians": 23
        }
      },
      {
        "level": 10,
        "expFactor": 592,
        "attrs": {
          "spirit": 20,
          "talent": 20,
          "meridians": 23
        }
      },
      {
        "level": 11,
        "expFactor": 656,
        "attrs": {
          "spirit": 20,
          "talent": 21,
          "meridians": 23
        }
      },
      {
        "level": 12,
        "expFactor": 728,
        "attrs": {
          "spirit": 20,
          "talent": 21,
          "meridians": 23
        }
      },
      {
        "level": 13,
        "expFactor": 808,
        "attrs": {
          "spirit": 20,
          "talent": 21,
          "meridians": 23
        }
      },
      {
        "level": 14,
        "expFactor": 0,
        "attrs": {
          "spirit": 20,
          "talent": 21,
          "meridians": 23
        }
      }
    ],
    "skills": []
  }
]
