[
  {
    "id": "stone_wall",
    "name": "石墙",
    "visual": { "tileType": "wall", "layer": "structure" },
    "placement": { "layer": "structure", "footprint": [{ "dx": 0, "dy": 0 }] },
    "topology": { "blocksMove": true, "blocksSight": true, "roomBoundary": 100, "shaShield": 20 },
    "fengShui": { "elementVector": { "earth": 10 }, "traits": ["structure.wall", "material.stone"], "stability": 6 },
    "economy": { "durabilityMultiplier": 50, "maxHp": 120, "cost": [{ "itemId": "stone", "count": 1 }] }
  },
  {
    "id": "wooden_door",
    "name": "木门",
    "visual": { "tileType": "door", "layer": "structure" },
    "placement": { "layer": "structure", "footprint": [{ "dx": 0, "dy": 0 }] },
    "topology": { "blocksMove": false, "blocksSight": false, "roomBoundary": 100, "opening": "door" },
    "fengShui": { "elementVector": { "wood": 4 }, "traits": ["opening.door"], "qiLeak": 2 },
    "economy": { "durabilityMultiplier": 14, "maxHp": 80, "cost": [{ "itemId": "wood", "count": 1 }] }
  },
  {
    "id": "wooden_window",
    "name": "木窗",
    "visual": { "tileType": "window", "layer": "structure" },
    "placement": { "layer": "structure", "footprint": [{ "dx": 0, "dy": 0 }] },
    "topology": { "blocksMove": true, "blocksSight": false, "roomBoundary": 100, "opening": "window" },
    "fengShui": { "elementVector": { "wood": 3 }, "traits": ["opening.window"], "comfort": 2 },
    "economy": { "durabilityMultiplier": 10, "maxHp": 60, "cost": [{ "itemId": "wood", "count": 1 }] }
  },
  {
    "id": "plain_floor",
    "name": "地板",
    "visual": { "tileType": "floor", "layer": "terrain" },
    "placement": { "layer": "floor", "footprint": [{ "dx": 0, "dy": 0 }], "allowOverlapLayers": ["structure", "furniture", "facility"] },
    "topology": { "roofCoverage": 100 },
    "fengShui": { "traits": ["floor.basic"], "stability": 2 },
    "economy": { "durabilityMultiplier": 1, "maxHp": 80, "cost": [{ "itemId": "wood", "count": 1 }] }
  },
  {
    "id": "scripture_platform",
    "name": "藏经台",
    "placement": { "layer": "facility", "footprint": [{ "dx": 0, "dy": 0 }] },
    "topology": { "blocksMove": true },
    "fengShui": { "elementVector": { "wood": 18, "earth": 4 }, "traits": ["facility.scripture_platform", "storage.scripture"], "comfort": 3, "stability": 10, "qiAffinity": 2 },
    "economy": { "buildTicks": 3600, "durabilityMultiplier": 100, "maxHp": 120, "cost": [{ "itemId": "wood", "count": 8 }] }
  }
]
